[
  {
    "name": "巧克力餅乾",
    "ingredients": {
      "麵粉": 2,
      "糖": 1,
      "雞蛋": 1,
      "奶油": 1,
      "巧克力": 1,
      "巧克力豆": 1
    }
  },
  {
    "name": "草莓蛋糕",
    "ingredients": {
      "海綿蛋糕": 1,
      "草莓": 2,
      "鮮奶油": 1,
      "糖": 1
    }
  },
  {
    "name": "藍莓派",
    "ingredients": {
      "麵粉": 1,
      "奶油": 1,
      "藍莓": 2,
      "糖": 1,
      "餅乾底": 1
    }
  },
  {
    "name": "檸檬塔",
    "ingredients": {
      "麵粉": 1,
      "奶油": 1,
      "檸檬": 2,
      "雞蛋": 1,
      "糖": 1,
      "餅乾底": 1
    }
  },
  {
    "name": "杏仁餅乾",
    "ingredients": {
      "麵粉": 1,
      "糖": 1,
      "奶油": 1,
      "杏仁": 2,
      "雞蛋": 1
    }
  },
  {
    "name": "芒果慕斯",
    "ingredients": {
      "芒果": 2,
      "鮮奶油": 1,
      "牛奶": 1,
      "糖": 1,
      "明膠": 1
    }
  },
  {
    "name": "抹茶蛋糕捲",
    "ingredients": {
      "麵粉": 1,
      "雞蛋": 2,
      "糖": 1,
      "抹茶粉": 1,
      "鮮奶油": 1
    }
  },
  {
    "name": "香蕉蛋糕",
    "ingredients": {
      "麵粉": 1,
      "香蕉": 2,
      "雞蛋": 1,
      "牛奶": 1,
      "糖": 1,
      "泡打粉": 1
    }
  }
] 